datalyzer/__init__.py
datalyzer/analyzer.py
datalyzer-0.1.dist-info/LICENSE
datalyzer-0.1.dist-info/METADATA
datalyzer-0.1.dist-info/WHEEL
datalyzer-0.1.dist-info/top_level.txt
datalyzer-0.1.dist-info/RECORD
