Metadata-Version: 2.1
Name: datalyzer
Version: 0.1
Summary: Biblioteka do analizy danych.
Home-page: https://github.com/TwojeImie/datalyzer
Author: Twoje Imię
Author-email: twoj.email@example.com
Classifier: Programming Language :: Python :: 3
Classifier: License :: OSI Approved :: MIT License
License-File: LICENSE
Requires-Dist: pandas
